django_typesense/__init__.py
django_typesense/admin.py
django_typesense/apps.py
django_typesense/changelist.py
django_typesense/collections.py
django_typesense/exceptions.py
django_typesense/fields.py
django_typesense/mixins.py
django_typesense/paginator.py
django_typesense/signals.py
django_typesense/typesense_client.py
django_typesense/utils.py
django_typesense/management/__init__.py
django_typesense/management/commands/__init__.py
django_typesense/management/commands/updatecollections.py
django_typesense/migrations/__init__.py
django_typesense/static/admin/js/search-typesense.js
tests/__init__.py
tests/collections.py
tests/factories.py
tests/models.py
tests/settings.py
tests/test_typesense_admin_mixin.py
tests/test_typesense_changelist.py
tests/test_typesense_fields.py
tests/test_typesense_methods.py
tests/test_typesense_model_mixin.py
tests/test_typesense_paginator.py
tests/test_typesense_signals.py
tests/test_typesense_utils.py
tests/utils.py
django_typesense-0.1.3.dist-info/LICENSE
django_typesense-0.1.3.dist-info/METADATA
django_typesense-0.1.3.dist-info/WHEEL
django_typesense-0.1.3.dist-info/top_level.txt
django_typesense-0.1.3.dist-info/RECORD
