Metadata-Version: 2.1
Name: django_typesense
Version: 0.1.3
Author: Siege Software
Author-email: info@siege.ai
Classifier: Development Status :: 3 - Alpha
Classifier: License :: OSI Approved :: MIT License
Classifier: Framework :: Django
Classifier: Intended Audience :: Developers
Classifier: Natural Language :: English
Classifier: Programming Language :: Python :: 3
Classifier: Operating System :: OS Independent
License-File: LICENSE
Requires-Dist: django
Requires-Dist: typesense
